webenginepy/__init__.py
webenginepy/engine.py
webenginepy-0.2.1.dist-info/licenses/License
webenginepy-0.2.1.dist-info/METADATA
webenginepy-0.2.1.dist-info/WHEEL
webenginepy-0.2.1.dist-info/top_level.txt
webenginepy-0.2.1.dist-info/RECORD
