Metadata-Version: 2.4
Name: webenginepy
Version: 0.2.1
Summary: Mini moteur web Python pour créer des sites web ultra simples sans framework
Author-email: Gabri <gabri@example.com>
License: MIT
Project-URL: Homepage, https://pypi.org/project/webenginepy/
Project-URL: Source, https://pypi.org/project/webenginepy/
Keywords: web,engine,http,site,minimal
Classifier: Programming Language :: Python :: 3
Classifier: License :: OSI Approved :: MIT License
Classifier: Operating System :: OS Independent
Requires-Python: >=3.8
License-File: License
Dynamic: license-file
